openai_load_balancer/__init__.py
openai_load_balancer/api_endpoint.py
openai_load_balancer/load_balancer.py
openai_load_balancer/openai_interface.py
tests/__init__.py
tests/test_api_endpoint.py
tests/test_load_balancer.py
tests/test_openai_interface.py
openai_load_balancer-0.1.1.dist-info/LICENSE
openai_load_balancer-0.1.1.dist-info/METADATA
openai_load_balancer-0.1.1.dist-info/WHEEL
openai_load_balancer-0.1.1.dist-info/top_level.txt
openai_load_balancer-0.1.1.dist-info/RECORD
