Metadata-Version: 2.1
Name: openai-load-balancer
Version: 0.1.1
Summary: The OpenAI Load Balancer is a Python library designed to distribute API requests across multiple endpoints (supports both OpenAI and Azure OpenAI). It implements a round-robin mechanism for load balancing and includes exponential backoff for retrying failed requests.
Home-page: https://github.com/Spryngtime/openai-load-balancer
Author: Rick Liu
Author-email: rick@spryngtime.com
License: MIT
Classifier: License :: OSI Approved :: MIT License
Classifier: Programming Language :: Python :: 3
Classifier: Programming Language :: Python :: 3.7
Classifier: Programming Language :: Python :: 3.8
License-File: LICENSE
Requires-Dist: openai
Requires-Dist: python-dotenv
Requires-Dist: tenacity
